[{"first_name": "Frederick", "last_name": "Wallace", "email": "ppayne@example.org"}, {"first_name": "Nicholas", "last_name": "Mccall", "email": "abigail64@example.org"}, {"first_name": "Donald", "last_name": "Williamson", "email": "joyce37@example.org"}, {"first_name": "Mary", "last_name": "Ward", "email": "melissarussell@example.org"}, {"first_name": "Kim", "last_name": "Morrison", "email": "andrew65@example.org"}, {"first_name": "Pam", "last_name": "Moss", "email": "justin62@example.net"}, {"first_name": "Eric", "last_name": "Randolph", "email": "juarezcarol@example.net"}, {"first_name": "Stacy", "last_name": "Brewer", "email": "robertsongerald@example.com"}, {"first_name": "Christopher", "last_name": "Wall", "email": "valerie91@example.org"}, {"first_name": "Jessica", "last_name": "Velez", "email": "miranda26@example.com"}, {"first_name": "Rebecca", "last_name": "Flores", "email": "murphymary@example.com"}, {"first_name": "Kathryn", "last_name": "Williams", "email": "scott97@example.org"}, {"first_name": "Cynthia", "last_name": "Green", "email": "jamesalexander@example.com"}, {"first_name": "Stephanie", "last_name": "Hall", "email": "edavis@example.com"}, {"first_name": "Misty", "last_name": "Cohen", "email": "cjenkins@example.org"}, {"first_name": "Bradley", "last_name": "Shaffer", "email": "laura68@example.net"}, {"first_name": "Tyler", "last_name": "Munoz", "email": "jillbrooks@example.com"}, {"first_name": "Anthony", "last_name": "Smith", "email": "bryanwendy@example.net"}, {"first_name": "Scott", "last_name": "Raymond", "email": "wendymeyer@example.com"}, {"first_name": "Ashley", "last_name": "Brown", "email": "colemanlaura@example.com"}, {"first_name": "Reginald", "last_name": "Higgins", "email": "vnichols@example.org"}, {"first_name": "Donna", "last_name": "Harris", "email": "katrina57@example.com"}, {"first_name": "Heidi", "last_name": "Osborne", "email": "albert10@example.com"}, {"first_name": "Jeffrey", "last_name": "Johnson", "email": "susan96@example.net"}, {"first_name": "Elizabeth", "last_name": "Dixon", "email": "michael73@example.net"}, {"first_name": "Jeffrey", "last_name": "Jensen", "email": "dominic22@example.net"}, {"first_name": "Mary", "last_name": "Singh", "email": "valeriesmith@example.net"}, {"first_name": "Amanda", "last_name": "Turner", "email": "boydjohn@example.com"}, {"first_name": "Philip", "last_name": "Lynch", "email": "steven43@example.net"}, {"first_name": "John", "last_name": "Rose", "email": "tnelson@example.com"}, {"first_name": "David", "last_name": "Wise", "email": "kyle39@example.com"}, {"first_name": "Michael", "last_name": "Moyer", "email": "mford@example.com"}, {"first_name": "Steven", "last_name": "Delacruz", "email": "bradley46@example.org"}, {"first_name": "Kelly", "last_name": "Evans", "email": "tperez@example.net"}, {"first_name": "Deanna", "last_name": "Williams", "email": "carrie90@example.com"}, {"first_name": "Rachel", "last_name": "Jackson", "email": "pamela41@example.com"}, {"first_name": "Henry", "last_name": "Todd", "email": "robertsmichael@example.com"}, {"first_name": "Stephen", "last_name": "Jones", "email": "tammyclark@example.com"}, {"first_name": "Amanda", "last_name": "Williams", "email": "michael72@example.org"}, {"first_name": "Matthew", "last_name": "Rogers", "email": "andresmith@example.net"}, {"first_name": "Michael", "last_name": "Hopkins", "email": "lopezmatthew@example.com"}, {"first_name": "Angelica", "last_name": "Martinez", "email": "georgeellis@example.net"}, {"first_name": "Brenda", "last_name": "Murray", "email": "cynthiawood@example.com"}, {"first_name": "Chelsea", "last_name": "Nguyen", "email": "john26@example.net"}, {"first_name": "James", "last_name": "Wilson", "email": "moorenicholas@example.org"}, {"first_name": "Andrew", "last_name": "Webb", "email": "zlopez@example.net"}, {"first_name": "Debra", "last_name": "Cox", "email": "david05@example.com"}, {"first_name": "Justin", "last_name": "Reynolds", "email": "cassandrabarnett@example.net"}, {"first_name": "John", "last_name": "Mcgrath", "email": "jasonrussell@example.com"}, {"first_name": "Karen", "last_name": "Rasmussen", "email": "dcampbell@example.org"}, {"first_name": "Timothy", "last_name": "Oneal", "email": "harrischarles@example.net"}, {"first_name": "Nicole", "last_name": "Wagner", "email": "daniel48@example.com"}, {"first_name": "Lacey", "last_name": "Dyer", "email": "melissamoore@example.net"}, {"first_name": "Dominique", "last_name": "Ford", "email": "yfowler@example.com"}, {"first_name": "Marcus", "last_name": "Wu", "email": "logan43@example.com"}, {"first_name": "Thomas", "last_name": "Lane", "email": "estradajeffrey@example.net"}, {"first_name": "Carolyn", "last_name": "Jenkins", "email": "hernandezrebecca@example.org"}, {"first_name": "Matthew", "last_name": "Young", "email": "jonathon00@example.net"}, {"first_name": "Robert", "last_name": "Young", "email": "bensonbenjamin@example.org"}, {"first_name": "John", "last_name": "Kane", "email": "carolcarr@example.com"}, {"first_name": "Nicholas", "last_name": "Woodard", "email": "joshuaevans@example.com"}, {"first_name": "Gary", "last_name": "Rogers", "email": "ialvarez@example.org"}, {"first_name": "Kelly", "last_name": "Daniels", "email": "dawnlarson@example.com"}, {"first_name": "Robert", "last_name": "Clark", "email": "jonesstephen@example.net"}, {"first_name": "Lee", "last_name": "Walters", "email": "kristen50@example.net"}, {"first_name": "Donald", "last_name": "Howard", "email": "colliermegan@example.org"}, {"first_name": "Ryan", "last_name": "Gutierrez", "email": "matthewhampton@example.org"}, {"first_name": "Linda", "last_name": "Hawkins", "email": "mayerbrianna@example.com"}, {"first_name": "Todd", "last_name": "Strickland", "email": "chavezrichard@example.org"}, {"first_name": "Paul", "last_name": "Brown", "email": "griffinemily@example.org"}, {"first_name": "Steven", "last_name": "Pennington", "email": "daniel30@example.org"}, {"first_name": "Ann", "last_name": "Mccarthy", "email": "tyler13@example.org"}, {"first_name": "Catherine", "last_name": "Ryan", "email": "james77@example.com"}, {"first_name": "Kenneth", "last_name": "Velasquez", "email": "sharon37@example.org"}, {"first_name": "Michael", "last_name": "Fernandez", "email": "iparker@example.net"}, {"first_name": "Linda", "last_name": "Tran", "email": "josephbeck@example.com"}, {"first_name": "Kathryn", "last_name": "Brown", "email": "rachelhale@example.com"}, {"first_name": "Mackenzie", "last_name": "Gordon", "email": "sandra26@example.org"}, {"first_name": "Colleen", "last_name": "Williams", "email": "carolwade@example.net"}, {"first_name": "William", "last_name": "Hoover", "email": "ssullivan@example.org"}, {"first_name": "Jeffrey", "last_name": "Fernandez", "email": "michaelhutchinson@example.org"}, {"first_name": "Sheri", "last_name": "Flynn", "email": "daughertyashlee@example.org"}, {"first_name": "Kyle", "last_name": "Miller", "email": "elaine62@example.org"}, {"first_name": "Christopher", "last_name": "Dalton", "email": "anthonycoleman@example.net"}, {"first_name": "Erin", "last_name": "Jordan", "email": "stephaniejohnson@example.net"}, {"first_name": "Amber", "last_name": "Simmons", "email": "ywest@example.org"}, {"first_name": "Chad", "last_name": "Campbell", "email": "cmcconnell@example.net"}, {"first_name": "Martin", "last_name": "Jimenez", "email": "michael47@example.com"}, {"first_name": "Joan", "last_name": "Kelly", "email": "vnewman@example.org"}, {"first_name": "Yolanda", "last_name": "Huffman", "email": "john67@example.org"}, {"first_name": "Joshua", "last_name": "Zimmerman", "email": "escott@example.net"}, {"first_name": "Dawn", "last_name": "Liu", "email": "rodriguezandrea@example.org"}, {"first_name": "Frances", "last_name": "Goodwin", "email": "chadbartlett@example.org"}, {"first_name": "David", "last_name": "Nichols", "email": "sthompson@example.org"}, {"first_name": "Diane", "last_name": "Warner", "email": "jasonwells@example.com"}, {"first_name": "Juan", "last_name": "Vargas", "email": "john93@example.com"}, {"first_name": "Michael", "last_name": "Ashley", "email": "rachel53@example.com"}, {"first_name": "Sarah", "last_name": "Bennett", "email": "anthony23@example.com"}, {"first_name": "Wesley", "last_name": "Parks", "email": "kmccann@example.net"}, {"first_name": "Frank", "last_name": "Oneill", "email": "rodriguezbradley@example.net"}]